{
  "name": "Multiplayer game",
  "description": "Tileset: https://merchant-shade.itch.io/16x16-puny-world\nCharacter: https://erisesra.itch.io/character-templates-pack\nLevel 1: https://ansimuz.itch.io/sunny-land-pixel-game-art",
  "levels": [
    {
      "name": "All together now",
      "description": "",
      "gameplayData": "",
      "layers": [
        {
          "name": "Stones 0",
          "gameplayData": "",
          "x": 320,
          "y": 80,
          "depth": 0.0,
          "tilesSheetFile": "media/punyworld-overworld-tileset.png",
          "tilesWidth": 16,
          "tilesHeight": 16,
          "visible": true,
          "groupId": "__main__",
          "tileMapFile": "tilemaps/level_000_layer_000.json"
        },
        {
          "name": "Stones 1",
          "gameplayData": "",
          "x": 528,
          "y": 400,
          "depth": 0.0,
          "tilesSheetFile": "media/punyworld-overworld-tileset.png",
          "tilesWidth": 16,
          "tilesHeight": 16,
          "visible": true,
          "groupId": "__main__",
          "tileMapFile": "tilemaps/level_000_layer_001.json"
        },
        {
          "name": "Stones 2",
          "gameplayData": "",
          "x": 656,
          "y": 80,
          "depth": 0.0,
          "tilesSheetFile": "media/punyworld-overworld-tileset.png",
          "tilesWidth": 16,
          "tilesHeight": 16,
          "visible": true,
          "groupId": "__main__",
          "tileMapFile": "tilemaps/level_000_layer_002.json"
        },
        {
          "name": "Stones 3",
          "gameplayData": "",
          "x": 48,
          "y": 400,
          "depth": 0.0,
          "tilesSheetFile": "media/punyworld-overworld-tileset.png",
          "tilesWidth": 16,
          "tilesHeight": 16,
          "visible": true,
          "groupId": "__main__",
          "tileMapFile": "tilemaps/level_000_layer_003.json"
        },
        {
          "name": "Gems Zone",
          "gameplayData": "",
          "x": 64,
          "y": 16,
          "depth": 0.0,
          "tilesSheetFile": "media/punyworld-overworld-tileset.png",
          "tilesWidth": 16,
          "tilesHeight": 16,
          "visible": true,
          "groupId": "__main__",
          "tileMapFile": "tilemaps/level_000_layer_004.json"
        },
        {
          "name": "Terrain",
          "gameplayData": "",
          "x": 0,
          "y": 0,
          "depth": 0.0,
          "tilesSheetFile": "media/punyworld-overworld-tileset.png",
          "tilesWidth": 16,
          "tilesHeight": 16,
          "visible": true,
          "groupId": "__main__",
          "tileMapFile": "tilemaps/level_000_layer_005.json"
        }
      ],
      "layerGroups": [
        {
          "id": "__main__",
          "name": "Main",
          "collapsed": false
        }
      ],
      "sprites": [
        {
          "name": "Hero 0",
          "gameplayData": "",
          "type": "Hero 0",
          "animationId": "anim_1772099194341380",
          "x": 32,
          "y": 32,
          "width": 20,
          "height": 20,
          "imageFile": "media/16x16 Idle-Sheet.png",
          "flipX": false,
          "flipY": false,
          "depth": 0.0,
          "groupId": "__main__"
        },
        {
          "name": "Gem Purple",
          "gameplayData": "",
          "type": "Gem Purple",
          "animationId": "anim_1772440074459800",
          "x": 50,
          "y": 475,
          "width": 15,
          "height": 15,
          "imageFile": "media/gem.png",
          "flipX": false,
          "flipY": false,
          "depth": 0.0,
          "groupId": "__main__"
        },
        {
          "name": "Gem Yellow",
          "gameplayData": "",
          "type": "Gem Yellow",
          "animationId": "anim_2",
          "x": 75,
          "y": 475,
          "width": 15,
          "height": 15,
          "imageFile": "media/gem.png",
          "flipX": false,
          "flipY": false,
          "depth": 0.0,
          "groupId": "__main__"
        },
        {
          "name": "Gem Green",
          "gameplayData": "",
          "type": "Gem Green",
          "animationId": "anim_1",
          "x": 100,
          "y": 475,
          "width": 15,
          "height": 15,
          "imageFile": "media/gem.png",
          "flipX": false,
          "flipY": false,
          "depth": 0.0,
          "groupId": "__main__"
        },
        {
          "name": "Gem Blue",
          "gameplayData": "",
          "type": "Gem Blue",
          "animationId": "anim_3",
          "x": 125,
          "y": 475,
          "width": 15,
          "height": 15,
          "imageFile": "media/gem.png",
          "flipX": false,
          "flipY": false,
          "depth": 0.0,
          "groupId": "__main__"
        }
      ],
      "spriteGroups": [
        {
          "id": "__main__",
          "name": "Main",
          "collapsed": false
        }
      ],
      "groupId": "__main__",
      "viewportWidth": 320,
      "viewportHeight": 180,
      "viewportX": 280,
      "viewportY": 175,
      "viewportAdaptation": "expand",
      "viewportInitialColor": "yellow",
      "viewportPreviewColor": "pink",
      "backgroundColorHex": "#000000",
      "depthSensitivity": 0.08,
      "zonesFile": "zones/level_000_zones.json",
      "pathsFile": "paths/level_000_paths.json"
    }
  ],
  "levelGroups": [
    {
      "id": "__main__",
      "name": "Main",
      "collapsed": false
    }
  ],
  "mediaAssets": [
    {
      "name": "Tileset",
      "fileName": "media/punyworld-overworld-tileset.png",
      "mediaType": "tileset",
      "tileWidth": 16,
      "tileHeight": 16,
      "selectionColorHex": "#FF2D55",
      "groupId": "__main__"
    },
    {
      "name": "Character Idle",
      "fileName": "media/16x16 Idle-Sheet.png",
      "mediaType": "spritesheet",
      "tileWidth": 20,
      "tileHeight": 20,
      "selectionColorHex": "#FFCC00",
      "groupId": "__main__"
    },
    {
      "name": "Character Walk",
      "fileName": "media/16x16 Walk-Sheet.png",
      "mediaType": "spritesheet",
      "tileWidth": 20,
      "tileHeight": 20,
      "selectionColorHex": "#FFCC00",
      "groupId": "__main__"
    },
    {
      "name": "Smoke",
      "fileName": "media/DragonDeath.png",
      "mediaType": "spritesheet",
      "tileWidth": 28,
      "tileHeight": 26,
      "selectionColorHex": "#FFCC00",
      "groupId": "__main__"
    },
    {
      "name": "Gem",
      "fileName": "media/gem.png",
      "mediaType": "spritesheet",
      "tileWidth": 15,
      "tileHeight": 15,
      "selectionColorHex": "#FFCC00",
      "groupId": "__main__"
    }
  ],
  "mediaGroups": [
    {
      "id": "__main__",
      "name": "Main",
      "collapsed": false
    }
  ],
  "zoneTypes": [
    {
      "name": "Wall",
      "color": "red"
    },
    {
      "name": "Ice",
      "color": "cyan"
    },
    {
      "name": "Sand",
      "color": "orange"
    }
  ],
  "animationsFile": "animations/animations.json"
}